{
    "annotations": {
        "list": []
    },
    "description": "Database and Business Metrics for Perpustakaan Microservices",
    "editable": true,
    "gnetId": null,
    "graphTooltip": 1,
    "id": null,
    "links": [],
    "panels": [
        {
            "collapsed": false,
            "gridPos": {
                "h": 1,
                "w": 24,
                "x": 0,
                "y": 0
            },
            "id": 100,
            "panels": [],
            "title": "🗄️ Database Connection Pool",
            "type": "row"
        },
        {
            "datasource": "Prometheus",
            "fieldConfig": {
                "defaults": {
                    "color": {
                        "mode": "palette-classic"
                    },
                    "custom": {
                        "axisLabel": "Connections",
                        "axisPlacement": "auto",
                        "barAlignment": 0,
                        "drawStyle": "line",
                        "fillOpacity": 20,
                        "gradientMode": "opacity",
                        "hideFrom": {
                            "legend": false,
                            "tooltip": false,
                            "viz": false
                        },
                        "lineInterpolation": "smooth",
                        "lineWidth": 2,
                        "pointSize": 5,
                        "scaleDistribution": {
                            "type": "linear"
                        },
                        "showPoints": "never",
                        "spanNulls": true,
                        "stacking": {
                            "group": "A",
                            "mode": "none"
                        },
                        "thresholdsStyle": {
                            "mode": "off"
                        }
                    },
                    "mappings": [],
                    "thresholds": {
                        "mode": "absolute",
                        "steps": [
                            {
                                "color": "green",
                                "value": null
                            }
                        ]
                    },
                    "unit": "short"
                }
            },
            "gridPos": {
                "h": 8,
                "w": 12,
                "x": 0,
                "y": 1
            },
            "id": 1,
            "options": {
                "legend": {
                    "calcs": [
                        "mean",
                        "max",
                        "lastNotNull"
                    ],
                    "displayMode": "table",
                    "placement": "bottom"
                },
                "tooltip": {
                    "mode": "multi",
                    "sort": "desc"
                }
            },
            "targets": [
                {
                    "expr": "hikaricp_connections_active{job=\"spring-boot-docker\"}",
                    "legendFormat": "{{application}} - Active",
                    "refId": "A"
                },
                {
                    "expr": "hikaricp_connections_idle{job=\"spring-boot-docker\"}",
                    "legendFormat": "{{application}} - Idle",
                    "refId": "B"
                },
                {
                    "expr": "hikaricp_connections_pending{job=\"spring-boot-docker\"}",
                    "legendFormat": "{{application}} - Pending",
                    "refId": "C"
                }
            ],
            "title": "🔗 HikariCP Connection Pool",
            "type": "timeseries"
        },
        {
            "datasource": "Prometheus",
            "fieldConfig": {
                "defaults": {
                    "color": {
                        "mode": "palette-classic"
                    },
                    "custom": {
                        "axisLabel": "Time",
                        "axisPlacement": "auto",
                        "barAlignment": 0,
                        "drawStyle": "line",
                        "fillOpacity": 10,
                        "gradientMode": "none",
                        "hideFrom": {
                            "legend": false,
                            "tooltip": false,
                            "viz": false
                        },
                        "lineInterpolation": "smooth",
                        "lineWidth": 2,
                        "pointSize": 5,
                        "scaleDistribution": {
                            "type": "linear"
                        },
                        "showPoints": "never",
                        "spanNulls": true,
                        "stacking": {
                            "group": "A",
                            "mode": "none"
                        },
                        "thresholdsStyle": {
                            "mode": "line"
                        }
                    },
                    "mappings": [],
                    "thresholds": {
                        "mode": "absolute",
                        "steps": [
                            {
                                "color": "green",
                                "value": null
                            },
                            {
                                "color": "yellow",
                                "value": 100
                            },
                            {
                                "color": "red",
                                "value": 500
                            }
                        ]
                    },
                    "unit": "ms"
                }
            },
            "gridPos": {
                "h": 8,
                "w": 12,
                "x": 12,
                "y": 1
            },
            "id": 2,
            "options": {
                "legend": {
                    "calcs": [
                        "mean",
                        "max",
                        "p95"
                    ],
                    "displayMode": "table",
                    "placement": "bottom"
                },
                "tooltip": {
                    "mode": "multi",
                    "sort": "desc"
                }
            },
            "targets": [
                {
                    "expr": "rate(hikaricp_connections_acquire_seconds_sum{job=\"spring-boot-docker\"}[1m]) / rate(hikaricp_connections_acquire_seconds_count{job=\"spring-boot-docker\"}[1m]) * 1000",
                    "legendFormat": "{{application}} - Acquire Time",
                    "refId": "A"
                },
                {
                    "expr": "rate(hikaricp_connections_usage_seconds_sum{job=\"spring-boot-docker\"}[1m]) / rate(hikaricp_connections_usage_seconds_count{job=\"spring-boot-docker\"}[1m]) * 1000",
                    "legendFormat": "{{application}} - Usage Time",
                    "refId": "B"
                }
            ],
            "title": "⏱️ Connection Pool Timing",
            "type": "timeseries"
        },
        {
            "collapsed": false,
            "gridPos": {
                "h": 1,
                "w": 24,
                "x": 0,
                "y": 9
            },
            "id": 101,
            "panels": [],
            "title": "📚 API Endpoints Performance",
            "type": "row"
        },
        {
            "datasource": "Prometheus",
            "fieldConfig": {
                "defaults": {
                    "color": {
                        "mode": "palette-classic"
                    },
                    "custom": {
                        "axisLabel": "Requests/min",
                        "axisPlacement": "auto",
                        "barAlignment": 0,
                        "drawStyle": "bars",
                        "fillOpacity": 80,
                        "gradientMode": "none",
                        "hideFrom": {
                            "legend": false,
                            "tooltip": false,
                            "viz": false
                        },
                        "lineInterpolation": "linear",
                        "lineWidth": 1,
                        "pointSize": 5,
                        "scaleDistribution": {
                            "type": "linear"
                        },
                        "showPoints": "never",
                        "spanNulls": true,
                        "stacking": {
                            "group": "A",
                            "mode": "normal"
                        },
                        "thresholdsStyle": {
                            "mode": "off"
                        }
                    },
                    "mappings": [],
                    "thresholds": {
                        "mode": "absolute",
                        "steps": [
                            {
                                "color": "green",
                                "value": null
                            }
                        ]
                    },
                    "unit": "short"
                }
            },
            "gridPos": {
                "h": 8,
                "w": 24,
                "x": 0,
                "y": 10
            },
            "id": 10,
            "options": {
                "legend": {
                    "calcs": [
                        "sum"
                    ],
                    "displayMode": "table",
                    "placement": "right"
                },
                "tooltip": {
                    "mode": "multi",
                    "sort": "desc"
                }
            },
            "targets": [
                {
                    "expr": "sum(increase(http_server_requests_seconds_count{job=\"spring-boot-docker\", uri=~\"/api/.*\"}[1m])) by (uri, method)",
                    "legendFormat": "{{method}} {{uri}}",
                    "refId": "A"
                }
            ],
            "title": "📊 API Endpoint Hits (per minute)",
            "type": "timeseries"
        },
        {
            "datasource": "Prometheus",
            "fieldConfig": {
                "defaults": {
                    "color": {
                        "mode": "thresholds"
                    },
                    "custom": {
                        "align": "auto",
                        "displayMode": "auto"
                    },
                    "mappings": [],
                    "thresholds": {
                        "mode": "absolute",
                        "steps": [
                            {
                                "color": "green",
                                "value": null
                            },
                            {
                                "color": "yellow",
                                "value": 0.5
                            },
                            {
                                "color": "red",
                                "value": 1
                            }
                        ]
                    }
                },
                "overrides": [
                    {
                        "matcher": {
                            "id": "byName",
                            "options": "Response Time (p95)"
                        },
                        "properties": [
                            {
                                "id": "unit",
                                "value": "s"
                            },
                            {
                                "id": "custom.displayMode",
                                "value": "color-background"
                            }
                        ]
                    },
                    {
                        "matcher": {
                            "id": "byName",
                            "options": "Total Requests"
                        },
                        "properties": [
                            {
                                "id": "unit",
                                "value": "short"
                            }
                        ]
                    }
                ]
            },
            "gridPos": {
                "h": 10,
                "w": 24,
                "x": 0,
                "y": 18
            },
            "id": 11,
            "options": {
                "footer": {
                    "enablePagination": false,
                    "fields": "",
                    "reducer": [
                        "sum"
                    ],
                    "show": false
                },
                "showHeader": true,
                "sortBy": [
                    {
                        "desc": true,
                        "displayName": "Total Requests"
                    }
                ]
            },
            "targets": [
                {
                    "expr": "topk(20, sum(increase(http_server_requests_seconds_count{job=\"spring-boot-docker\", uri=~\"/api/.*\"}[1h])) by (application, method, uri))",
                    "format": "table",
                    "instant": true,
                    "legendFormat": "",
                    "refId": "A"
                }
            ],
            "title": "📋 Top API Endpoints (Last Hour)",
            "transformations": [
                {
                    "id": "organize",
                    "options": {
                        "excludeByName": {
                            "Time": true
                        },
                        "indexByName": {},
                        "renameByName": {
                            "application": "Service",
                            "method": "Method",
                            "uri": "Endpoint",
                            "Value": "Total Requests"
                        }
                    }
                }
            ],
            "type": "table"
        },
        {
            "collapsed": false,
            "gridPos": {
                "h": 1,
                "w": 24,
                "x": 0,
                "y": 28
            },
            "id": 102,
            "panels": [],
            "title": "⚠️ Error Analysis",
            "type": "row"
        },
        {
            "datasource": "Prometheus",
            "fieldConfig": {
                "defaults": {
                    "color": {
                        "mode": "palette-classic"
                    },
                    "custom": {
                        "axisLabel": "Errors",
                        "axisPlacement": "auto",
                        "barAlignment": 0,
                        "drawStyle": "bars",
                        "fillOpacity": 80,
                        "gradientMode": "none",
                        "hideFrom": {
                            "legend": false,
                            "tooltip": false,
                            "viz": false
                        },
                        "lineInterpolation": "linear",
                        "lineWidth": 1,
                        "pointSize": 5,
                        "scaleDistribution": {
                            "type": "linear"
                        },
                        "showPoints": "never",
                        "spanNulls": true,
                        "stacking": {
                            "group": "A",
                            "mode": "normal"
                        },
                        "thresholdsStyle": {
                            "mode": "off"
                        }
                    },
                    "mappings": [],
                    "thresholds": {
                        "mode": "absolute",
                        "steps": [
                            {
                                "color": "red",
                                "value": null
                            }
                        ]
                    },
                    "unit": "short"
                }
            },
            "gridPos": {
                "h": 8,
                "w": 12,
                "x": 0,
                "y": 29
            },
            "id": 20,
            "options": {
                "legend": {
                    "calcs": [
                        "sum"
                    ],
                    "displayMode": "table",
                    "placement": "bottom"
                },
                "tooltip": {
                    "mode": "multi",
                    "sort": "desc"
                }
            },
            "targets": [
                {
                    "expr": "sum(increase(http_server_requests_seconds_count{job=\"spring-boot-docker\", status=~\"4..\"}[5m])) by (application, status)",
                    "legendFormat": "{{application}} - {{status}}",
                    "refId": "A"
                }
            ],
            "title": "🟡 Client Errors (4xx)",
            "type": "timeseries"
        },
        {
            "datasource": "Prometheus",
            "fieldConfig": {
                "defaults": {
                    "color": {
                        "mode": "palette-classic"
                    },
                    "custom": {
                        "axisLabel": "Errors",
                        "axisPlacement": "auto",
                        "barAlignment": 0,
                        "drawStyle": "bars",
                        "fillOpacity": 80,
                        "gradientMode": "none",
                        "hideFrom": {
                            "legend": false,
                            "tooltip": false,
                            "viz": false
                        },
                        "lineInterpolation": "linear",
                        "lineWidth": 1,
                        "pointSize": 5,
                        "scaleDistribution": {
                            "type": "linear"
                        },
                        "showPoints": "never",
                        "spanNulls": true,
                        "stacking": {
                            "group": "A",
                            "mode": "normal"
                        },
                        "thresholdsStyle": {
                            "mode": "off"
                        }
                    },
                    "mappings": [],
                    "thresholds": {
                        "mode": "absolute",
                        "steps": [
                            {
                                "color": "red",
                                "value": null
                            }
                        ]
                    },
                    "unit": "short"
                }
            },
            "gridPos": {
                "h": 8,
                "w": 12,
                "x": 12,
                "y": 29
            },
            "id": 21,
            "options": {
                "legend": {
                    "calcs": [
                        "sum"
                    ],
                    "displayMode": "table",
                    "placement": "bottom"
                },
                "tooltip": {
                    "mode": "multi",
                    "sort": "desc"
                }
            },
            "targets": [
                {
                    "expr": "sum(increase(http_server_requests_seconds_count{job=\"spring-boot-docker\", status=~\"5..\"}[5m])) by (application, status, uri)",
                    "legendFormat": "{{application}} - {{status}} - {{uri}}",
                    "refId": "A"
                }
            ],
            "title": "🔴 Server Errors (5xx)",
            "type": "timeseries"
        },
        {
            "datasource": "Prometheus",
            "fieldConfig": {
                "defaults": {
                    "color": {
                        "mode": "thresholds"
                    },
                    "mappings": [],
                    "max": 100,
                    "min": 0,
                    "thresholds": {
                        "mode": "absolute",
                        "steps": [
                            {
                                "color": "red",
                                "value": null
                            },
                            {
                                "color": "yellow",
                                "value": 95
                            },
                            {
                                "color": "green",
                                "value": 99
                            }
                        ]
                    },
                    "unit": "percent"
                }
            },
            "gridPos": {
                "h": 6,
                "w": 6,
                "x": 0,
                "y": 37
            },
            "id": 22,
            "options": {
                "orientation": "auto",
                "reduceOptions": {
                    "calcs": [
                        "lastNotNull"
                    ],
                    "fields": "",
                    "values": false
                },
                "showThresholdLabels": false,
                "showThresholdMarkers": true
            },
            "targets": [
                {
                    "expr": "(sum(rate(http_server_requests_seconds_count{job=\"spring-boot-docker\", application=\"anggota\", status=~\"2..\"}[5m])) / sum(rate(http_server_requests_seconds_count{job=\"spring-boot-docker\", application=\"anggota\"}[5m]))) * 100",
                    "legendFormat": "",
                    "refId": "A"
                }
            ],
            "title": "✅ Anggota Success Rate",
            "type": "gauge"
        },
        {
            "datasource": "Prometheus",
            "fieldConfig": {
                "defaults": {
                    "color": {
                        "mode": "thresholds"
                    },
                    "mappings": [],
                    "max": 100,
                    "min": 0,
                    "thresholds": {
                        "mode": "absolute",
                        "steps": [
                            {
                                "color": "red",
                                "value": null
                            },
                            {
                                "color": "yellow",
                                "value": 95
                            },
                            {
                                "color": "green",
                                "value": 99
                            }
                        ]
                    },
                    "unit": "percent"
                }
            },
            "gridPos": {
                "h": 6,
                "w": 6,
                "x": 6,
                "y": 37
            },
            "id": 23,
            "options": {
                "orientation": "auto",
                "reduceOptions": {
                    "calcs": [
                        "lastNotNull"
                    ],
                    "fields": "",
                    "values": false
                },
                "showThresholdLabels": false,
                "showThresholdMarkers": true
            },
            "targets": [
                {
                    "expr": "(sum(rate(http_server_requests_seconds_count{job=\"spring-boot-docker\", application=\"buku\", status=~\"2..\"}[5m])) / sum(rate(http_server_requests_seconds_count{job=\"spring-boot-docker\", application=\"buku\"}[5m]))) * 100",
                    "legendFormat": "",
                    "refId": "A"
                }
            ],
            "title": "✅ Buku Success Rate",
            "type": "gauge"
        },
        {
            "datasource": "Prometheus",
            "fieldConfig": {
                "defaults": {
                    "color": {
                        "mode": "thresholds"
                    },
                    "mappings": [],
                    "max": 100,
                    "min": 0,
                    "thresholds": {
                        "mode": "absolute",
                        "steps": [
                            {
                                "color": "red",
                                "value": null
                            },
                            {
                                "color": "yellow",
                                "value": 95
                            },
                            {
                                "color": "green",
                                "value": 99
                            }
                        ]
                    },
                    "unit": "percent"
                }
            },
            "gridPos": {
                "h": 6,
                "w": 6,
                "x": 12,
                "y": 37
            },
            "id": 24,
            "options": {
                "orientation": "auto",
                "reduceOptions": {
                    "calcs": [
                        "lastNotNull"
                    ],
                    "fields": "",
                    "values": false
                },
                "showThresholdLabels": false,
                "showThresholdMarkers": true
            },
            "targets": [
                {
                    "expr": "(sum(rate(http_server_requests_seconds_count{job=\"spring-boot-docker\", application=\"peminjaman\", status=~\"2..\"}[5m])) / sum(rate(http_server_requests_seconds_count{job=\"spring-boot-docker\", application=\"peminjaman\"}[5m]))) * 100",
                    "legendFormat": "",
                    "refId": "A"
                }
            ],
            "title": "✅ Peminjaman Success Rate",
            "type": "gauge"
        },
        {
            "datasource": "Prometheus",
            "fieldConfig": {
                "defaults": {
                    "color": {
                        "mode": "thresholds"
                    },
                    "mappings": [],
                    "max": 100,
                    "min": 0,
                    "thresholds": {
                        "mode": "absolute",
                        "steps": [
                            {
                                "color": "red",
                                "value": null
                            },
                            {
                                "color": "yellow",
                                "value": 95
                            },
                            {
                                "color": "green",
                                "value": 99
                            }
                        ]
                    },
                    "unit": "percent"
                }
            },
            "gridPos": {
                "h": 6,
                "w": 6,
                "x": 18,
                "y": 37
            },
            "id": 25,
            "options": {
                "orientation": "auto",
                "reduceOptions": {
                    "calcs": [
                        "lastNotNull"
                    ],
                    "fields": "",
                    "values": false
                },
                "showThresholdLabels": false,
                "showThresholdMarkers": true
            },
            "targets": [
                {
                    "expr": "(sum(rate(http_server_requests_seconds_count{job=\"spring-boot-docker\", application=\"pengembalian\", status=~\"2..\"}[5m])) / sum(rate(http_server_requests_seconds_count{job=\"spring-boot-docker\", application=\"pengembalian\"}[5m]))) * 100",
                    "legendFormat": "",
                    "refId": "A"
                }
            ],
            "title": "✅ Pengembalian Success Rate",
            "type": "gauge"
        }
    ],
    "refresh": "10s",
    "schemaVersion": 30,
    "style": "dark",
    "tags": [
        "database",
        "api",
        "errors",
        "perpustakaan"
    ],
    "templating": {
        "list": []
    },
    "time": {
        "from": "now-1h",
        "to": "now"
    },
    "timepicker": {},
    "timezone": "browser",
    "title": "Perpustakaan - Database & API Metrics",
    "uid": "perpustakaan-db-api",
    "version": 1
}